grammark/__init__.py
resources/__init__.py
resources/academic.json
resources/eggcorns.json
resources/grammar.json
resources/nominalizations.json
resources/passive_voice.json
resources/sentences.json
resources/transitions.json
resources/wordiness.json
py_grammark-0.0.2.dist-info/LICENSE
py_grammark-0.0.2.dist-info/METADATA
py_grammark-0.0.2.dist-info/WHEEL
py_grammark-0.0.2.dist-info/top_level.txt
py_grammark-0.0.2.dist-info/RECORD
