Metadata-Version: 2.1
Name: py-grammark
Version: 0.0.2
Summary: Checks to improve scientific writing. See https://github.com/markfullmer/grammark for more information.
Home-page: https://github.com/highkite/py-grammark
Author: Thomas Osterland
Author-email: highway.ita07@web.de
License: UNKNOWN
Platform: UNKNOWN
Classifier: Programming Language :: Python :: 3
Classifier: License :: OSI Approved :: MIT License
Classifier: Operating System :: OS Independent
Requires-Python: >=3.6
License-File: LICENSE
